rtl/lane_fsm.v
module lane_fsm #(
    parameter TIMER_WIDTH = 16,
    parameter GREEN_MIN = 50,   
    parameter GREEN_STEP = 25,  
    parameter YELLOW_TIME = 15  
)(
    input  wire clk,
    input  wire reset,
    input  wire grant,              
    input  wire ped_req,               
    input  wire [1:0] density,         
    output reg  green,
    output reg  yellow,
    output reg  red
);

    localparam S_RED    = 2'd0;
    localparam S_GREEN  = 2'd1;
    localparam S_YELLOW = 2'd2;

    reg [1:0] state, next_state;
    reg [TIMER_WIDTH-1:0] timer, next_timer;

    always @(posedge clk or posedge reset) begin
        if (reset) begin
            state <= S_RED;
            timer <= 0;
        end else begin
            state <= next_state;
            timer <= next_timer;
        end
    end

    always @(*) begin
        next_state = state;
        next_timer = timer;

        case (state)
            S_RED: begin
                if (grant) begin
                    next_state = S_GREEN;
                    next_timer = GREEN_MIN + (density * GREEN_STEP);
                    if (ped_req) next_timer = next_timer + GREEN_STEP;
                end
            end

            S_GREEN: begin
                if (timer == 0) begin
                    next_state = S_YELLOW;
                    next_timer = YELLOW_TIME; 
                end else begin
                    next_timer = timer - 1;
                end
            end

            S_YELLOW: begin
                if (timer == 0) begin
                    next_state = S_RED;
                    next_timer = 0;
                end else begin
                    next_timer = timer - 1;
                end
            end

            default: begin
                next_state = S_RED;
                next_timer = 0;
            end
        endcase
    end

    always @(*) begin
        green  = (state == S_GREEN);
        yellow = (state == S_YELLOW);
        red    = (state == S_RED);
    end

endmodule

rtl/arbiter.v
module arbiter (
    input  wire [1:0] dens_N,
    input  wire [1:0] dens_E,
    input  wire [1:0] dens_S,
    input  wire [1:0] dens_W,
    input  wire       ped_N,
    input  wire       ped_E,
    input  wire       ped_S,
    input  wire       ped_W,
    input  wire       emergency_N,
    input  wire       emergency_E,
    input  wire       emergency_S,
    input  wire       emergency_W,
    output reg        grant_N,
    output reg        grant_E,
    output reg        grant_S,
    output reg        grant_W
);
    integer score_N, score_E, score_S, score_W;
    always @(*) begin
        grant_N = 0; grant_E = 0; grant_S = 0; grant_W = 0;

        if (emergency_N | emergency_E | emergency_S | emergency_W) begin
            score_N = (emergency_N ? 100 : 0) + dens_N + (ped_N ? 2 : 0);
            score_E = (emergency_E ? 100 : 0) + dens_E + (ped_E ? 2 : 0);
            score_S = (emergency_S ? 100 : 0) + dens_S + (ped_S ? 2 : 0);
            score_W = (emergency_W ? 100 : 0) + dens_W + (ped_W ? 2 : 0);
        end else begin
            score_N = dens_N + (ped_N ? 2 : 0);
            score_E = dens_E + (ped_E ? 2 : 0);
            score_S = dens_S + (ped_S ? 2 : 0);
            score_W = dens_W + (ped_W ? 2 : 0);
        end
        
        if (score_N >= score_E && score_N >= score_S && score_N >= score_W) grant_N = 1;
        else if (score_E >= score_N && score_E >= score_S && score_E >= score_W) grant_E = 1;
        else if (score_S >= score_N && score_S >= score_E && score_S >= score_W) grant_S = 1;
        else grant_W = 1;
    end
endmodule

rtl/top.v
// rtl/top.v
module top (
    input  wire clk,
    input  wire reset,
    input  wire [1:0] sensor_N,
    input  wire [1:0] sensor_E,
    input  wire [1:0] sensor_S,
    input  wire [1:0] sensor_W,
    input  wire       ped_N,
    input  wire       ped_E,
    input  wire       ped_S,
    input  wire       ped_W,
    input  wire       emergency_N,
    input  wire       emergency_E,
    input  wire       emergency_S,
    input  wire       emergency_W,
    output wire green_N, yellow_N, red_N,
    output wire green_E, yellow_E, red_E,
    output wire green_S, yellow_S, red_S,
    output wire green_W, yellow_W, red_W
);
    wire grant_N, grant_E, grant_S, grant_W;

    arbiter arb_u (
        .dens_N(sensor_N), .dens_E(sensor_E), .dens_S(sensor_S), .dens_W(sensor_W),
        .ped_N(ped_N), .ped_E(ped_E), .ped_S(ped_S), .ped_W(ped_W),
        .emergency_N(emergency_N), .emergency_E(emergency_E), .emergency_S(emergency_S), .emergency_W(emergency_W),
        .grant_N(grant_N), .grant_E(grant_E), .grant_S(grant_S), .grant_W(grant_W)
    );

    lane_fsm #(.GREEN_MIN(100), .GREEN_STEP(50), .YELLOW_TIME(30)) laneN(
        .clk(clk), .reset(reset), .grant(grant_N), .ped_req(ped_N), .density(sensor_N),
        .green(green_N), .yellow(yellow_N), .red(red_N)
    );

    lane_fsm laneE(
        .clk(clk), .reset(reset), .grant(grant_E), .ped_req(ped_E), .density(sensor_E),
        .green(green_E), .yellow(yellow_E), .red(red_E)
    );

    lane_fsm laneS(
        .clk(clk), .reset(reset), .grant(grant_S), .ped_req(ped_S), .density(sensor_S),
        .green(green_S), .yellow(yellow_S), .red(red_S)
    );

    lane_fsm laneW(
        .clk(clk), .reset(reset), .grant(grant_W), .ped_req(ped_W), .density(sensor_W),
        .green(green_W), .yellow(yellow_W), .red(red_W)
    );

endmodule

tb/tb_top.v
// tb/tb_top.v
`timescale 1ns/1ns
module tb_top;
    reg clk;
    reg reset;

    // sensors (0..3)
    reg [1:0] sN, sE, sS, sW;
    reg pedN, pedE, pedS, pedW;
    reg emN, emE, emS, emW;

    wire gN, yN, rN, gE, yE, rE, gS, yS, rS, gW, yW, rW;

    top uut (
        .clk(clk), .reset(reset),
        .sensor_N(sN), .sensor_E(sE), .sensor_S(sS), .sensor_W(sW),
        .ped_N(pedN), .ped_E(pedE), .ped_S(pedS), .ped_W(pedW),
        .emergency_N(emN), .emergency_E(emE), .emergency_S(emS), .emergency_W(emW),
        .green_N(gN), .yellow_N(yN), .red_N(rN),
        .green_E(gE), .yellow_E(yE), .red_E(rE),
        .green_S(gS), .yellow_S(yS), .red_S(rS),
        .green_W(gW), .yellow_W(yW), .red_W(rW)
    );

    // clock: period 10 ns
    initial clk = 0;
    always #5 clk = ~clk;

    // waveform
    initial begin
        $dumpfile("tb_top.vcd");
        $dumpvars(0, tb_top);
    end

    initial begin
        // init
        reset = 1;
        sN = 0; sE = 0; sS = 0; sW = 0;
        pedN = 0; pedE = 0; pedS = 0; pedW = 0;
        emN = 0; emE = 0; emS = 0; emW = 0;
        #20;
        reset = 0;

        // Scenario A: low traffic everywhere (rotating by arbiter tie-break)
        sN=0; sE=0; sS=0; sW=0;
        #500;

        // Scenario B: heavy N and S traffic
        sN=3; sE=1; sS=3; sW=0;
        #1000;

        // Scenario C: pedestrian request at East
        pedE = 1;
        #300;
        pedE = 0;
        #700;

        // Scenario D: sudden surge West
        sW = 3; sN = 1; sE = 0; sS = 0;
        #1000;

        // Scenario E: emergency at South
        emS = 1;
        #400;
        emS = 0;
        #400;

        $finish;
    end
endmodule

tb_top.vcd
$date
	Thu Oct 16 23:15:20 2025
$end
$version
	Icarus Verilog
$end
$timescale
	1ns
$end
$scope module tb_top $end
$var wire 1 ! yW $end
$var wire 1 " yS $end
$var wire 1 # yN $end
$var wire 1 $ yE $end
$var wire 1 % rW $end
$var wire 1 & rS $end
$var wire 1 ' rN $end
$var wire 1 ( rE $end
$var wire 1 ) gW $end
$var wire 1 * gS $end
$var wire 1 + gN $end
$var wire 1 , gE $end
$var reg 1 - clk $end
$var reg 1 . emE $end
$var reg 1 / emN $end
$var reg 1 0 emS $end
$var reg 1 1 emW $end
$var reg 1 2 pedE $end
$var reg 1 3 pedN $end
$var reg 1 4 pedS $end
$var reg 1 5 pedW $end
$var reg 1 6 reset $end
$var reg 2 7 sE [1:0] $end
$var reg 2 8 sN [1:0] $end
$var reg 2 9 sS [1:0] $end
$var reg 2 : sW [1:0] $end
$scope module uut $end
$var wire 1 - clk $end
$var wire 1 . emergency_E $end
$var wire 1 / emergency_N $end
$var wire 1 0 emergency_S $end
$var wire 1 1 emergency_W $end
$var wire 1 2 ped_E $end
$var wire 1 3 ped_N $end
$var wire 1 4 ped_S $end
$var wire 1 5 ped_W $end
$var wire 1 6 reset $end
$var wire 2 ; sensor_E [1:0] $end
$var wire 2 < sensor_N [1:0] $end
$var wire 2 = sensor_S [1:0] $end
$var wire 2 > sensor_W [1:0] $end
$var wire 1 ! yellow_W $end
$var wire 1 " yellow_S $end
$var wire 1 # yellow_N $end
$var wire 1 $ yellow_E $end
$var wire 1 % red_W $end
$var wire 1 & red_S $end
$var wire 1 ' red_N $end
$var wire 1 ( red_E $end
$var wire 1 ) green_W $end
$var wire 1 * green_S $end
$var wire 1 + green_N $end
$var wire 1 , green_E $end
$var wire 1 ? grant_W $end
$var wire 1 @ grant_S $end
$var wire 1 A grant_N $end
$var wire 1 B grant_E $end
$scope module arb_u $end
$var wire 2 C dens_E [1:0] $end
$var wire 2 D dens_N [1:0] $end
$var wire 2 E dens_S [1:0] $end
$var wire 2 F dens_W [1:0] $end
$var wire 1 . emergency_E $end
$var wire 1 / emergency_N $end
$var wire 1 0 emergency_S $end
$var wire 1 1 emergency_W $end
$var wire 1 2 ped_E $end
$var wire 1 3 ped_N $end
$var wire 1 4 ped_S $end
$var wire 1 5 ped_W $end
$var reg 1 B grant_E $end
$var reg 1 A grant_N $end
$var reg 1 @ grant_S $end
$var reg 1 ? grant_W $end
$var integer 32 G score_E [31:0] $end
$var integer 32 H score_N [31:0] $end
$var integer 32 I score_S [31:0] $end
$var integer 32 J score_W [31:0] $end
$upscope $end
$scope module laneE $end
$var wire 1 - clk $end
$var wire 2 K density [1:0] $end
$var wire 1 B grant $end
$var wire 1 2 ped_req $end
$var wire 1 6 reset $end
$var parameter 32 L GREEN_MIN $end
$var parameter 32 M GREEN_STEP $end
$var parameter 2 N S_GREEN $end
$var parameter 2 O S_RED $end
$var parameter 2 P S_YELLOW $end
$var parameter 32 Q TIMER_WIDTH $end
$var parameter 32 R YELLOW_TIME $end
$var reg 1 , green $end
$var reg 2 S next_state [1:0] $end
$var reg 16 T next_timer [15:0] $end
$var reg 1 ( red $end
$var reg 2 U state [1:0] $end
$var reg 16 V timer [15:0] $end
$var reg 1 $ yellow $end
$upscope $end
$scope module laneN $end
$var wire 1 - clk $end
$var wire 2 W density [1:0] $end
$var wire 1 A grant $end
$var wire 1 3 ped_req $end
$var wire 1 6 reset $end
$var parameter 32 X GREEN_MIN $end
$var parameter 32 Y GREEN_STEP $end
$var parameter 2 Z S_GREEN $end
$var parameter 2 [ S_RED $end
$var parameter 2 \ S_YELLOW $end
$var parameter 32 ] TIMER_WIDTH $end
$var parameter 32 ^ YELLOW_TIME $end
$var reg 1 + green $end
$var reg 2 _ next_state [1:0] $end
$var reg 16 ` next_timer [15:0] $end
$var reg 1 ' red $end
$var reg 2 a state [1:0] $end
$var reg 16 b timer [15:0] $end
$var reg 1 # yellow $end
$upscope $end
$scope module laneS $end
$var wire 1 - clk $end
$var wire 2 c density [1:0] $end
$var wire 1 @ grant $end
$var wire 1 4 ped_req $end
$var wire 1 6 reset $end
$var parameter 32 d GREEN_MIN $end
$var parameter 32 e GREEN_STEP $end
$var parameter 2 f S_GREEN $end
$var parameter 2 g S_RED $end
$var parameter 2 h S_YELLOW $end
$var parameter 32 i TIMER_WIDTH $end
$var parameter 32 j YELLOW_TIME $end
$var reg 1 * green $end
$var reg 2 k next_state [1:0] $end
$var reg 16 l next_timer [15:0] $end
$var reg 1 & red $end
$var reg 2 m state [1:0] $end
$var reg 16 n timer [15:0] $end
$var reg 1 " yellow $end
$upscope $end
$scope module laneW $end
$var wire 1 - clk $end
$var wire 2 o density [1:0] $end
$var wire 1 ? grant $end
$var wire 1 5 ped_req $end
$var wire 1 6 reset $end
$var parameter 32 p GREEN_MIN $end
$var parameter 32 q GREEN_STEP $end
$var parameter 2 r S_GREEN $end
$var parameter 2 s S_RED $end
$var parameter 2 t S_YELLOW $end
$var parameter 32 u TIMER_WIDTH $end
$var parameter 32 v YELLOW_TIME $end
$var reg 1 ) green $end
$var reg 2 w next_state [1:0] $end
$var reg 16 x next_timer [15:0] $end
$var reg 1 % red $end
$var reg 2 y state [1:0] $end
$var reg 16 z timer [15:0] $end
$var reg 1 ! yellow $end
$upscope $end
$upscope $end
$upscope $end
$enddefinitions $end
$comment Show the parameter values. $end
$dumpall
b1111 v
b10000 u
b10 t
b0 s
b1 r
b11001 q
b110010 p
b1111 j
b10000 i
b10 h
b0 g
b1 f
b11001 e
b110010 d
b11110 ^
b10000 ]
b10 \
b0 [
b1 Z
b110010 Y
b1100100 X
b1111 R
b10000 Q
b10 P
b0 O
b1 N
b11001 M
b110010 L
$end
#0
$dumpvars
b0 z
b0 y
b0 x
b0 w
b0 o
b0 n
b0 m
b0 l
b0 k
b0 c
b0 b
b0 a
b1100100 `
b1 _
b0 W
b0 V
b0 U
b0 T
b0 S
b0 K
b0 J
b0 I
b0 H
b0 G
b0 F
b0 E
b0 D
b0 C
0B
1A
0@
0?
b0 >
b0 =
b0 <
b0 ;
b0 :
b0 9
b0 8
b0 7
16
05
04
03
02
01
00
0/
0.
0-
0,
0+
0*
0)
1(
1'
1&
1%
0$
0#
0"
0!
$end
#5
1-
#10
0-
#15
1-
#20
0-
06
#25
0'
1+
b1100011 `
b1100100 b
b1 a
1-
#30
0-
#35
b1100010 `
b1100011 b
1-
#40
0-
#45
b1100001 `
b1100010 b
1-
#50
0-
#55
b1100000 `
b1100001 b
1-
#60
0-
#65
b1011111 `
b1100000 b
1-
#70
0-
#75
b1011110 `
b1011111 b
1-
#80
0-
#85
b1011101 `
b1011110 b
1-
#90
0-
#95
b1011100 `
b1011101 b
1-
#100
0-
#105
b1011011 `
b1011100 b
1-
#110
0-
#115
b1011010 `
b1011011 b
1-
#120
0-
#125
b1011001 `
b1011010 b
1-
#130
0-
#135
b1011000 `
b1011001 b
1-
#140
0-
#145
b1010111 `
b1011000 b
1-
#150
0-
#155
b1010110 `
b1010111 b
1-
#160
0-
#165
b1010101 `
b1010110 b
1-
#170
0-
#175
b1010100 `
b1010101 b
1-
#180
0-
#185
b1010011 `
b1010100 b
1-
#190
0-
#195
b1010010 `
b1010011 b
1-
#200
0-
#205
b1010001 `
b1010010 b
1-
#210
0-
#215
b1010000 `
b1010001 b
1-
#220
0-
#225
b1001111 `
b1010000 b
1-
#230
0-
#235
b1001110 `
b1001111 b
1-
#240
0-
#245
b1001101 `
b1001110 b
1-
#250
0-
#255
b1001100 `
b1001101 b
1-
#260
0-
#265
b1001011 `
b1001100 b
1-
#270
0-
#275
b1001010 `
b1001011 b
1-
#280
0-
#285
b1001001 `
b1001010 b
1-
#290
0-
#295
b1001000 `
b1001001 b
1-
#300
0-
#305
b1000111 `
b1001000 b
1-
#310
0-
#315
b1000110 `
b1000111 b
1-
#320
0-
#325
b1000101 `
b1000110 b
1-
#330
0-
#335
b1000100 `
b1000101 b
1-
#340
0-
#345
b1000011 `
b1000100 b
1-
#350
0-
#355
b1000010 `
b1000011 b
1-
#360
0-
#365
b1000001 `
b1000010 b
1-
#370
0-
#375
b1000000 `
b1000001 b
1-
#380
0-
#385
b111111 `
b1000000 b
1-
#390
0-
#395
b111110 `
b111111 b
1-
#400
0-
#405
b111101 `
b111110 b
1-
#410
0-
#415
b111100 `
b111101 b
1-
#420
0-
#425
b111011 `
b111100 b
1-
#430
0-
#435
b111010 `
b111011 b
1-
#440
0-
#445
b111001 `
b111010 b
1-
#450
0-
#455
b111000 `
b111001 b
1-
#460
0-
#465
b110111 `
b111000 b
1-
#470
0-
#475
b110110 `
b110111 b
1-
#480
0-
#485
b110101 `
b110110 b
1-
#490
0-
#495
b110100 `
b110101 b
1-
#500
0-
#505
b110011 `
b110100 b
1-
#510
0-
#515
b110010 `
b110011 b
1-
#520
b11 I
b1 G
b11 H
1A
b110010 `
0-
b11 9
b11 =
b11 E
b11 c
b1 7
b1 ;
b1 C
b1 K
b11 8
b11 <
b11 D
b11 W
#525
b110001 `
b110010 b
1-
#530
0-
#535
b110000 `
b110001 b
1-
#540
0-
#545
b101111 `
b110000 b
1-
#550
0-
#555
b101110 `
b101111 b
1-
#560
0-
#565
b101101 `
b101110 b
1-
#570
0-
#575
b101100 `
b101101 b
1-
#580
0-
#585
b101011 `
b101100 b
1-
#590
0-
#595
b101010 `
b101011 b
1-
#600
0-
#605
b101001 `
b101010 b
1-
#610
0-
#615
b101000 `
b101001 b
1-
#620
0-
#625
b100111 `
b101000 b
1-
#630
0-
#635
b100110 `
b100111 b
1-
#640
0-
#645
b100101 `
b100110 b
1-
#650
0-
#655
b100100 `
b100101 b
1-
#660
0-
#665
b100011 `
b100100 b
1-
#670
0-
#675
b100010 `
b100011 b
1-
#680
0-
#685
b100001 `
b100010 b
1-
#690
0-
#695
b100000 `
b100001 b
1-
#700
0-
#705
b11111 `
b100000 b
1-
#710
0-
#715
b11110 `
b11111 b
1-
#720
0-
#725
b11101 `
b11110 b
1-
#730
0-
#735
b11100 `
b11101 b
1-
#740
0-
#745
b11011 `
b11100 b
1-
#750
0-
#755
b11010 `
b11011 b
1-
#760
0-
#765
b11001 `
b11010 b
1-
#770
0-
#775
b11000 `
b11001 b
1-
#780
0-
#785
b10111 `
b11000 b
1-
#790
0-
#795
b10110 `
b10111 b
1-
#800
0-
#805
b10101 `
b10110 b
1-
#810
0-
#815
b10100 `
b10101 b
1-
#820
0-
#825
b10011 `
b10100 b
1-
#830
0-
#835
b10010 `
b10011 b
1-
#840
0-
#845
b10001 `
b10010 b
1-
#850
0-
#855
b10000 `
b10001 b
1-
#860
0-
#865
b1111 `
b10000 b
1-
#870
0-
#875
b1110 `
b1111 b
1-
#880
0-
#885
b1101 `
b1110 b
1-
#890
0-
#895
b1100 `
b1101 b
1-
#900
0-
#905
b1011 `
b1100 b
1-
#910
0-
#915
b1010 `
b1011 b
1-
#920
0-
#925
b1001 `
b1010 b
1-
#930
0-
#935
b1000 `
b1001 b
1-
#940
0-
#945
b111 `
b1000 b
1-
#950
0-
#955
b110 `
b111 b
1-
#960
0-
#965
b101 `
b110 b
1-
#970
0-
#975
b100 `
b101 b
1-
#980
0-
#985
b11 `
b100 b
1-
#990
0-
#995
b10 `
b11 b
1-
#1000
0-
#1005
b1 `
b10 b
1-
#1010
0-
#1015
b0 `
b1 b
1-
#1020
0-
#1025
b11110 `
b10 _
b0 b
1-
#1030
0-
#1035
1#
0+
b11101 `
b11110 b
b10 a
1-
#1040
0-
#1045
b11100 `
b11101 b
1-
#1050
0-
#1055
b11011 `
b11100 b
1-
#1060
0-
#1065
b11010 `
b11011 b
1-
#1070
0-
#1075
b11001 `
b11010 b
1-
#1080
0-
#1085
b11000 `
b11001 b
1-
#1090
0-
#1095
b10111 `
b11000 b
1-
#1100
0-
#1105
b10110 `
b10111 b
1-
#1110
0-
#1115
b10101 `
b10110 b
1-
#1120
0-
#1125
b10100 `
b10101 b
1-
#1130
0-
#1135
b10011 `
b10100 b
1-
#1140
0-
#1145
b10010 `
b10011 b
1-
#1150
0-
#1155
b10001 `
b10010 b
1-
#1160
0-
#1165
b10000 `
b10001 b
1-
#1170
0-
#1175
b1111 `
b10000 b
1-
#1180
0-
#1185
b1110 `
b1111 b
1-
#1190
0-
#1195
b1101 `
b1110 b
1-
#1200
0-
#1205
b1100 `
b1101 b
1-
#1210
0-
#1215
b1011 `
b1100 b
1-
#1220
0-
#1225
b1010 `
b1011 b
1-
#1230
0-
#1235
b1001 `
b1010 b
1-
#1240
0-
#1245
b1000 `
b1001 b
1-
#1250
0-
#1255
b111 `
b1000 b
1-
#1260
0-
#1265
b110 `
b111 b
1-
#1270
0-
#1275
b101 `
b110 b
1-
#1280
0-
#1285
b100 `
b101 b
1-
#1290
0-
#1295
b11 `
b100 b
1-
#1300
0-
#1305
b10 `
b11 b
1-
#1310
0-
#1315
b1 `
b10 b
1-
#1320
0-
#1325
b0 `
b1 b
1-
#1330
0-
#1335
b0 _
b0 b
1-
#1340
0-
#1345
1'
0#
b11111010 `
b1 _
b0 a
1-
#1350
0-
#1355
0'
1+
b11111001 `
b11111010 b
b1 a
1-
#1360
0-
#1365
b11111000 `
b11111001 b
1-
#1370
0-
#1375
b11110111 `
b11111000 b
1-
#1380
0-
#1385
b11110110 `
b11110111 b
1-
#1390
0-
#1395
b11110101 `
b11110110 b
1-
#1400
0-
#1405
b11110100 `
b11110101 b
1-
#1410
0-
#1415
b11110011 `
b11110100 b
1-
#1420
0-
#1425
b11110010 `
b11110011 b
1-
#1430
0-
#1435
b11110001 `
b11110010 b
1-
#1440
0-
#1445
b11110000 `
b11110001 b
1-
#1450
0-
#1455
b11101111 `
b11110000 b
1-
#1460
0-
#1465
b11101110 `
b11101111 b
1-
#1470
0-
#1475
b11101101 `
b11101110 b
1-
#1480
0-
#1485
b11101100 `
b11101101 b
1-
#1490
0-
#1495
b11101011 `
b11101100 b
1-
#1500
0-
#1505
b11101010 `
b11101011 b
1-
#1510
0-
#1515
b11101001 `
b11101010 b
1-
#1520
b11101001 `
b11 G
1A
0-
12
#1525
b11101000 `
b11101001 b
1-
#1530
0-
#1535
b11100111 `
b11101000 b
1-
#1540
0-
#1545
b11100110 `
b11100111 b
1-
#1550
0-
#1555
b11100101 `
b11100110 b
1-
#1560
0-
#1565
b11100100 `
b11100101 b
1-
#1570
0-
#1575
b11100011 `
b11100100 b
1-
#1580
0-
#1585
b11100010 `
b11100011 b
1-
#1590
0-
#1595
b11100001 `
b11100010 b
1-
#1600
0-
#1605
b11100000 `
b11100001 b
1-
#1610
0-
#1615
b11011111 `
b11100000 b
1-
#1620
0-
#1625
b11011110 `
b11011111 b
1-
#1630
0-
#1635
b11011101 `
b11011110 b
1-
#1640
0-
#1645
b11011100 `
b11011101 b
1-
#1650
0-
#1655
b11011011 `
b11011100 b
1-
#1660
0-
#1665
b11011010 `
b11011011 b
1-
#1670
0-
#1675
b11011001 `
b11011010 b
1-
#1680
0-
#1685
b11011000 `
b11011001 b
1-
#1690
0-
#1695
b11010111 `
b11011000 b
1-
#1700
0-
#1705
b11010110 `
b11010111 b
1-
#1710
0-
#1715
b11010101 `
b11010110 b
1-
#1720
0-
#1725
b11010100 `
b11010101 b
1-
#1730
0-
#1735
b11010011 `
b11010100 b
1-
#1740
0-
#1745
b11010010 `
b11010011 b
1-
#1750
0-
#1755
b11010001 `
b11010010 b
1-
#1760
0-
#1765
b11010000 `
b11010001 b
1-
#1770
0-
#1775
b11001111 `
b11010000 b
1-
#1780
0-
#1785
b11001110 `
b11001111 b
1-
#1790
0-
#1795
b11001101 `
b11001110 b
1-
#1800
0-
#1805
b11001100 `
b11001101 b
1-
#1810
0-
#1815
b11001011 `
b11001100 b
1-
#1820
b11001011 `
b1 G
1A
0-
02
#1825
b11001010 `
b11001011 b
1-
#1830
0-
#1835
b11001001 `
b11001010 b
1-
#1840
0-
#1845
b11001000 `
b11001001 b
1-
#1850
0-
#1855
b11000111 `
b11001000 b
1-
#1860
0-
#1865
b11000110 `
b11000111 b
1-
#1870
0-
#1875
b11000101 `
b11000110 b
1-
#1880
0-
#1885
b11000100 `
b11000101 b
1-
#1890
0-
#1895
b11000011 `
b11000100 b
1-
#1900
0-
#1905
b11000010 `
b11000011 b
1-
#1910
0-
#1915
b11000001 `
b11000010 b
1-
#1920
0-
#1925
b11000000 `
b11000001 b
1-
#1930
0-
#1935
b10111111 `
b11000000 b
1-
#1940
0-
#1945
b10111110 `
b10111111 b
1-
#1950
0-
#1955
b10111101 `
b10111110 b
1-
#1960
0-
#1965
b10111100 `
b10111101 b
1-
#1970
0-
#1975
b10111011 `
b10111100 b
1-
#1980
0-
#1985
b10111010 `
b10111011 b
1-
#1990
0-
#1995
b10111001 `
b10111010 b
1-
#2000
0-
#2005
b10111000 `
b10111001 b
1-
#2010
0-
#2015
b10110111 `
b10111000 b
1-
#2020
0-
#2025
b10110110 `
b10110111 b
1-
#2030
0-
#2035
b10110101 `
b10110110 b
1-
#2040
0-
#2045
b10110100 `
b10110101 b
1-
#2050
0-
#2055
b10110011 `
b10110100 b
1-
#2060
0-
#2065
b10110010 `
b10110011 b
1-
#2070
0-
#2075
b10110001 `
b10110010 b
1-
#2080
0-
#2085
b10110000 `
b10110001 b
1-
#2090
0-
#2095
b10101111 `
b10110000 b
1-
#2100
0-
#2105
b10101110 `
b10101111 b
1-
#2110
0-
#2115
b10101101 `
b10101110 b
1-
#2120
0-
#2125
b10101100 `
b10101101 b
1-
#2130
0-
#2135
b10101011 `
b10101100 b
1-
#2140
0-
#2145
b10101010 `
b10101011 b
1-
#2150
0-
#2155
b10101001 `
b10101010 b
1-
#2160
0-
#2165
b10101000 `
b10101001 b
1-
#2170
0-
#2175
b10100111 `
b10101000 b
1-
#2180
0-
#2185
b10100110 `
b10100111 b
1-
#2190
0-
#2195
b10100101 `
b10100110 b
1-
#2200
0-
#2205
b10100100 `
b10100101 b
1-
#2210
0-
#2215
b10100011 `
b10100100 b
1-
#2220
0-
#2225
b10100010 `
b10100011 b
1-
#2230
0-
#2235
b10100001 `
b10100010 b
1-
#2240
0-
#2245
b10100000 `
b10100001 b
1-
#2250
0-
#2255
b10011111 `
b10100000 b
1-
#2260
0-
#2265
b10011110 `
b10011111 b
1-
#2270
0-
#2275
b10011101 `
b10011110 b
1-
#2280
0-
#2285
b10011100 `
b10011101 b
1-
#2290
0-
#2295
b10011011 `
b10011100 b
1-
#2300
0-
#2305
b10011010 `
b10011011 b
1-
#2310
0-
#2315
b10011001 `
b10011010 b
1-
#2320
0-
#2325
b10011000 `
b10011001 b
1-
#2330
0-
#2335
b10010111 `
b10011000 b
1-
#2340
0-
#2345
b10010110 `
b10010111 b
1-
#2350
0-
#2355
b10010101 `
b10010110 b
1-
#2360
0-
#2365
b10010100 `
b10010101 b
1-
#2370
0-
#2375
b10010011 `
b10010100 b
1-
#2380
0-
#2385
b10010010 `
b10010011 b
1-
#2390
0-
#2395
b10010001 `
b10010010 b
1-
#2400
0-
#2405
b10010000 `
b10010001 b
1-
#2410
0-
#2415
b10001111 `
b10010000 b
1-
#2420
0-
#2425
b10001110 `
b10001111 b
1-
#2430
0-
#2435
b10001101 `
b10001110 b
1-
#2440
0-
#2445
b10001100 `
b10001101 b
1-
#2450
0-
#2455
b10001011 `
b10001100 b
1-
#2460
0-
#2465
b10001010 `
b10001011 b
1-
#2470
0-
#2475
b10001001 `
b10001010 b
1-
#2480
0-
#2485
b10001000 `
b10001001 b
1-
#2490
0-
#2495
b10000111 `
b10001000 b
1-
#2500
0-
#2505
b10000110 `
b10000111 b
1-
#2510
0-
#2515
b10000101 `
b10000110 b
1-
#2520
b1111101 x
b1 w
b10000101 `
1?
b11 J
b0 I
b0 G
b1 H
0A
0-
b0 9
b0 =
b0 E
b0 c
b0 7
b0 ;
b0 C
b0 K
b1 8
b1 <
b1 D
b1 W
b11 :
b11 >
b11 F
b11 o
#2525
0%
1)
b1111100 x
b10000100 `
b1111101 z
b1 y
b10000101 b
1-
#2530
0-
#2535
b10000011 `
b1111011 x
b10000100 b
b1111100 z
1-
#2540
0-
#2545
b1111010 x
b10000010 `
b1111011 z
b10000011 b
1-
#2550
0-
#2555
b10000001 `
b1111001 x
b10000010 b
b1111010 z
1-
#2560
0-
#2565
b1111000 x
b10000000 `
b1111001 z
b10000001 b
1-
#2570
0-
#2575
b1111111 `
b1110111 x
b10000000 b
b1111000 z
1-
#2580
0-
#2585
b1110110 x
b1111110 `
b1110111 z
b1111111 b
1-
#2590
0-
#2595
b1111101 `
b1110101 x
b1111110 b
b1110110 z
1-
#2600
0-
#2605
b1110100 x
b1111100 `
b1110101 z
b1111101 b
1-
#2610
0-
#2615
b1111011 `
b1110011 x
b1111100 b
b1110100 z
1-
#2620
0-
#2625
b1110010 x
b1111010 `
b1110011 z
b1111011 b
1-
#2630
0-
#2635
b1111001 `
b1110001 x
b1111010 b
b1110010 z
1-
#2640
0-
#2645
b1110000 x
b1111000 `
b1110001 z
b1111001 b
1-
#2650
0-
#2655
b1110111 `
b1101111 x
b1111000 b
b1110000 z
1-
#2660
0-
#2665
b1101110 x
b1110110 `
b1101111 z
b1110111 b
1-
#2670
0-
#2675
b1110101 `
b1101101 x
b1110110 b
b1101110 z
1-
#2680
0-
#2685
b1101100 x
b1110100 `
b1101101 z
b1110101 b
1-
#2690
0-
#2695
b1110011 `
b1101011 x
b1110100 b
b1101100 z
1-
#2700
0-
#2705
b1101010 x
b1110010 `
b1101011 z
b1110011 b
1-
#2710
0-
#2715
b1110001 `
b1101001 x
b1110010 b
b1101010 z
1-
#2720
0-
#2725
b1101000 x
b1110000 `
b1101001 z
b1110001 b
1-
#2730
0-
#2735
b1101111 `
b1100111 x
b1110000 b
b1101000 z
1-
#2740
0-
#2745
b1100110 x
b1101110 `
b1100111 z
b1101111 b
1-
#2750
0-
#2755
b1101101 `
b1100101 x
b1101110 b
b1100110 z
1-
#2760
0-
#2765
b1100100 x
b1101100 `
b1100101 z
b1101101 b
1-
#2770
0-
#2775
b1101011 `
b1100011 x
b1101100 b
b1100100 z
1-
#2780
0-
#2785
b1100010 x
b1101010 `
b1100011 z
b1101011 b
1-
#2790
0-
#2795
b1101001 `
b1100001 x
b1101010 b
b1100010 z
1-
#2800
0-
#2805
b1100000 x
b1101000 `
b1100001 z
b1101001 b
1-
#2810
0-
#2815
b1100111 `
b1011111 x
b1101000 b
b1100000 z
1-
#2820
0-
#2825
b1011110 x
b1100110 `
b1011111 z
b1100111 b
1-
#2830
0-
#2835
b1100101 `
b1011101 x
b1100110 b
b1011110 z
1-
#2840
0-
#2845
b1011100 x
b1100100 `
b1011101 z
b1100101 b
1-
#2850
0-
#2855
b1100011 `
b1011011 x
b1100100 b
b1011100 z
1-
#2860
0-
#2865
b1011010 x
b1100010 `
b1011011 z
b1100011 b
1-
#2870
0-
#2875
b1100001 `
b1011001 x
b1100010 b
b1011010 z
1-
#2880
0-
#2885
b1011000 x
b1100000 `
b1011001 z
b1100001 b
1-
#2890
0-
#2895
b1011111 `
b1010111 x
b1100000 b
b1011000 z
1-
#2900
0-
#2905
b1010110 x
b1011110 `
b1010111 z
b1011111 b
1-
#2910
0-
#2915
b1011101 `
b1010101 x
b1011110 b
b1010110 z
1-
